common.py
msk_funcs-1.0.dist-info/METADATA
msk_funcs-1.0.dist-info/WHEEL
msk_funcs-1.0.dist-info/top_level.txt
msk_funcs-1.0.dist-info/RECORD
