Metadata-Version: 2.1
Name: msk-funcs
Version: 1.0
Summary: some useful functions, welcome to use!
Home-page: https://github.com/solomsk/msk_funcs/
Author: msk
Author-email: solo_msk@163.com
License: MIT
Platform: UNKNOWN
